{
  "unit": 15,
  "topic": "Let's play ball!",
  "vocabulary": [
    { "word": "bat",        "image": "/images/unit-15/bat.png" },
    { "word": "beach",      "image": "/images/unit-15/beach.png" },
    { "word": "boat",       "image": "/images/unit-15/boat.png" },
    { "word": "pail",       "image": "/images/unit-15/pail.png" },
    { "word": "crab",       "image": "/images/unit-15/crab.png" },
    { "word": "ice pop",    "image": "/images/unit-15/ice-pop.png" },
    { "word": "sandcastle", "image": "/images/unit-15/sandcastle.png" },
    { "word": "shell",      "image": "/images/unit-15/shell.png" },
    { "word": "shovel",     "image": "/images/unit-15/shovel.png" },
    { "word": "sunscreen",  "image": "/images/unit-15/sunscreen.png" },
    { "word": "the ocean",  "image": "/images/unit-15/the-ocean.png" }
  ],
  "grammar_patterns": [
    {
      "pattern": "Let's [verb] [object].",
      "examples": [
        "Let's play ball!",
        "Let's find shells.",
        "Let's make sandcastles!",
        "Let's count the shells.",
        "Let's find the crabs.",
        "Let's make a sandcastle.",
        "Let's walk on the beach.",
        "Let's swim in the ocean."
      ]
    },
    {
      "pattern": "That's a good idea.",
      "examples": [
        "Let's play ball! That's a good idea.",
        "Let's find shells. That's a good idea."
      ]
    },
    {
      "pattern": "Don't forget your [noun].",
      "examples": [
        "Don't forget your hat.",
        "Don't forget your sunscreen.",
        "Don't forget your shovel.",
        "Don't forget your pail."
      ]
    }
  ],
  "key_sentences": [
    "Let's play ball!",
    "Let's make a sandcastle.",
    "Let's swim in the ocean.",
    "That's a good idea.",
    "Don't forget your hat.",
    "Don't forget your sunscreen."
  ]
}
