{
  "unit": 13,
  "topic": "Clean up!",
  "vocabulary": [
    { "word": "bed",      "image": "/images/unit-13/bed.png" },
    { "word": "cabinet",  "image": "/images/unit-13/cabinet.png" },
    { "word": "pillow",   "image": "/images/unit-13/pillow.png" },
    { "word": "blanket",  "image": "/images/unit-13/blanket.png" },
    { "word": "rug",      "image": "/images/unit-13/rug.png" },
    { "word": "shelf",    "image": "/images/unit-13/shelf.png" }
  ],
  "numbers": [
    "eleven", "twelve", "thirteen", "fourteen", "fifteen",
    "sixteen", "seventeen", "eighteen", "nineteen", "twenty"
  ],
  "prepositions": ["in", "on", "under"],
  "grammar_patterns": [
    {
      "pattern": "There's a [noun] [preposition] my/the [noun].",
      "examples": [
        "There's a train under my bed.",
        "There's a car in the cabinet.",
        "There's a teddy bear on my bed.",
        "There's a soccer ball under the bed."
      ]
    },
    {
      "pattern": "There are [noun]s [preposition] my/the [noun].",
      "examples": [
        "There are books on the shelf.",
        "There are coats in my cabinet.",
        "There are dolls on my rug.",
        "There are pillows on the bed."
      ]
    },
    {
      "pattern": "There are [number] [noun]s [preposition] my/the [noun].",
      "examples": [
        "There are three coats in the cabinet.",
        "There are two books on my shelf.",
        "There are twelve dolls on the rug.",
        "There are fifteen books on my shelf."
      ]
    }
  ],
  "key_sentences": [
    "There's a teddy bear on my bed.",
    "There are three dolls on the rug.",
    "There's a car in my cabinet.",
    "There are books on the shelf.",
    "There's a soccer ball under my bed.",
    "There are twelve pillows on the bed."
  ]
}
